{
  "main": {
    "id": "c5923f4009959bf5",
    "type": "split",
    "children": [
      {
        "id": "583353402314e843",
        "type": "tabs",
        "children": [
          {
            "id": "f7ca162c320d338a",
            "type": "leaf",
            "state": {
              "type": "markdown",
              "state": {
                "file": "Tech/WebSockets/socket.io.md",
                "mode": "source",
                "source": false
              }
            }
          }
        ]
      }
    ],
    "direction": "vertical"
  },
  "left": {
    "id": "449e44faf9da8e2f",
    "type": "split",
    "children": [
      {
        "id": "9758137bf1c32c2a",
        "type": "tabs",
        "children": [
          {
            "id": "567cc77b8238ddc0",
            "type": "leaf",
            "state": {
              "type": "file-explorer",
              "state": {
                "sortOrder": "alphabetical"
              }
            }
          },
          {
            "id": "9e3dd2998de4e20c",
            "type": "leaf",
            "state": {
              "type": "search",
              "state": {
                "query": "",
                "matchingCase": false,
                "explainSearch": false,
                "collapseAll": false,
                "extraContext": false,
                "sortOrder": "alphabetical"
              }
            }
          },
          {
            "id": "7210e8fa57725d71",
            "type": "leaf",
            "state": {
              "type": "bookmarks",
              "state": {}
            }
          }
        ]
      }
    ],
    "direction": "horizontal",
    "width": 300
  },
  "right": {
    "id": "720db7314345e1f3",
    "type": "split",
    "children": [
      {
        "id": "c27a73c878faa868",
        "type": "tabs",
        "children": [
          {
            "id": "36c500f8d11df0b1",
            "type": "leaf",
            "state": {
              "type": "backlink",
              "state": {
                "file": "Tech/WebSockets/socket.io.md",
                "collapseAll": false,
                "extraContext": false,
                "sortOrder": "alphabetical",
                "showSearch": false,
                "searchQuery": "",
                "backlinkCollapsed": false,
                "unlinkedCollapsed": true
              }
            }
          },
          {
            "id": "7922f7494304311c",
            "type": "leaf",
            "state": {
              "type": "outgoing-link",
              "state": {
                "file": "Tech/WebSockets/socket.io.md",
                "linksCollapsed": false,
                "unlinkedCollapsed": true
              }
            }
          },
          {
            "id": "59a7e3c5a60bd068",
            "type": "leaf",
            "state": {
              "type": "tag",
              "state": {
                "sortOrder": "frequency",
                "useHierarchy": true
              }
            }
          },
          {
            "id": "ccd7c238f83097ba",
            "type": "leaf",
            "state": {
              "type": "outline",
              "state": {
                "file": "Tech/WebSockets/socket.io.md"
              }
            }
          }
        ]
      }
    ],
    "direction": "horizontal",
    "width": 300,
    "collapsed": true
  },
  "left-ribbon": {
    "hiddenItems": {
      "switcher:Open quick switcher": false,
      "graph:Open graph view": false,
      "canvas:Create new canvas": false,
      "daily-notes:Open today's daily note": false,
      "templates:Insert template": false,
      "command-palette:Open command palette": false,
      "obsidian-excalidraw-plugin:Create new drawing": false
    }
  },
  "active": "f7ca162c320d338a",
  "lastOpenFiles": [
    "Screenshot 2024-09-16 at 2.43.25 AM.png",
    "Tech/WebSockets/Screenshot 2024-09-16 at 2.33.17 AM.png",
    "0 - Index/BinarySearch.md",
    "Arrays/Medium/12-SpiralMatrix.md",
    "0 - Index/Tech.md",
    "Tech/WebSockets/socket.io.md",
    "Tech/WebSockets",
    "Arrays/Medium/11-setMatrixBy0.md",
    "0 - Templates/Questions.md",
    "Arrays/Medium/7-Next Permutation.md",
    "0 - Index/Array Medium.md",
    "Tech/kafka/Kafka Apache.md",
    "Tech/kafka",
    "Tech/kafka/Screenshot 2024-09-15 at 10.50.57 PM.png",
    "Tech/kafka/Screenshot 2024-09-15 at 9.27.54 PM.png",
    "Tech/kafka/Screenshot 2024-09-15 at 9.19.49 PM.png",
    "Tech/kafka/Screenshot 2024-09-15 at 8.47.59 PM.png",
    "Tech/kafka/Screenshot 2024-09-15 at 8.31.08 PM.png",
    "Tech/kafka/Screenshot 2024-09-15 at 8.30.38 PM.png",
    "Tech/kafka/Screenshot 2024-09-15 at 8.18.34 PM.png",
    "Tech/kafka/Screenshot 2024-09-15 at 8.15.41 PM.png",
    "Tech",
    "Untitled.canvas",
    "Arrays/Medium/2-Sorting0,1,2.md",
    "2.BinarySearch/1-LowerBound.md",
    "2.BinarySearch/3-SearchInsertPosition.md",
    "2.BinarySearch/2-upperBound.md",
    "2.BinarySearch/3-SearchInsertPosition.cpp",
    "2.BinarySearch/LowerBound.md",
    "2.BinarySearch",
    "Arrays/Medium/1-2SumProblem.md",
    "Arrays/Medium/1716920519-1-2-3.md",
    "Arrays/Medium/10-Set matrix 0.md",
    "Arrays/Medium/9-LongestConsecutiveSequence.md",
    "Arrays/Medium/10-Set Matrix 0.md",
    "Arrays/Medium/8-Leadder In Arrays.md",
    "Arrays/Medium/9-LongestConsecutiveSequence.cpp",
    "Arrays/Medium/5-BuyNSellStock.md",
    "Arrays/Medium/6-Rearrang By Sign.md",
    "Arrays/Medium/6-Rearrange Element By Sign",
    "Arrays/Medium/4-kadene's Algorithm.md",
    "Arrays/Medium/3-MajorityElement.md",
    "0 - Index",
    "Arrays/Medium/Untitled/Untitled.md",
    "Arrays/Medium/Untitled",
    "Arrays/Medium"
  ]
}